msread/__init__.py
msread/centroid.py
msread/constants.py
msread/header.py
msread/masslist.py
msread/mgf_reader.py
msread/ms_reader.py
msread/mzdata_reader.py
msread/mzml_reader.py
msread/mzxml_reader.py
msread/scan.py
msread/thermo_reader.py
msread/xy_reader.py
msread-0.10.1.dist-info/LICENSE
msread-0.10.1.dist-info/METADATA
msread-0.10.1.dist-info/WHEEL
msread-0.10.1.dist-info/top_level.txt
msread-0.10.1.dist-info/RECORD
