Metadata-Version: 2.1
Name: msread
Version: 0.10.1
Summary: Mass spectrometry data reading library
Home-page: https://github.com/xxao/msread
Author: Martin Strohalm
Author-email: 
License: MIT
Classifier: Development Status :: 4 - Beta
Classifier: Programming Language :: Python :: 3 :: Only
Classifier: Operating System :: OS Independent
Classifier: License :: OSI Approved :: MIT License
Classifier: Topic :: Scientific/Engineering
Classifier: Intended Audience :: Science/Research
License-File: LICENSE
Requires-Dist: numpy
